final_test04/__init__.py
final_test04/adaboost.py
final_test04/grad_boost.py
final_test04/knn.py
final_test04/logistic.py
final_test04/mlp.py
final_test04/my_func.py
final_test04/perceptron.py
final_test04/random_forest.py
final_test04/sgd.py
final_test04/support_vector.py
final_test04/untitled0.py
final_test04/visualize.py
final_test04/xgboost.py
final_test_04-0.1.0.dist-info/LICENSE
final_test_04-0.1.0.dist-info/METADATA
final_test_04-0.1.0.dist-info/WHEEL
final_test_04-0.1.0.dist-info/top_level.txt
final_test_04-0.1.0.dist-info/RECORD
